Workbook

Sheet 1. Raw Data
A1: CustomerID | B1: FullName | C1: Age | D1: City | E1: JoinDate | F1: Churn | G1: OrderID | H1: OrderDate | I1: ShipMode | J1: ProductID | K1: ProductName | L1: Category | M1: Price | N1: Cost | O1: Quantity | P1: Discount | Q1: Days_Since_Last_Order | R1: Total_Orders
A2: 2126 | B2: CUSTOMER_0 | C2: 35 | D2: Mansoura | E2: 02-08-2023 | F2: 0 | G2: 11420 | H2: 02-08-2023 | I2: Same Day | J2: 135 | K2: Product_135 | L2: Home Appliances | M2: 712.82 | N2: 334.36 | O2: 1 | Q2: 518 | R2: 4
A3: 2459 | B3: Customer_1 | C3: 54 | D3: Cairo | E3: 08/16/2020 | F3: 0 | G3: 12597 | H3: 08/16/2020 | I3: Express | J3: 119 | K3: Product_119 | L3: Home Appliances | M3: 148.6 | N3: 76.56 | O3: 2 | P3: 0.05 | Q3: 661 | R3: 6
A4: 1860 | B4: Customer_2 | C4: 60 | D4: Mansoura | E4: 02/21/2020 | F4: 1 | G4: 10496 | H4: 02/21/2020 | I4: Same Day | J4: 113 | K4: Product_113 | L4: Clothing | M4: 1039.74 | N4: 640.86 | O4: 1 | P4: 0.05 | Q4: 1094 | R4: 3
A5: 2294 | B5: Customer_3 | C5: 17 | D5: Cairo | E5: 07/17/2021 | F5: 0 | G5: 12220 | H5: 07/17/2021 | I5: Same Day | J5: 105 | K5: Product_105 | L5: Electronics | M5: 117.63 | N5: 57.56 | O5: 3 | Q5: 673 | R5: 5
A6: 2130 | B6: Customer_4 | C6: 32 | D6: Luxor | E6: 16-05-2021 | F6: 0 | G6: 10104 | H6: 16-05-2021 | I6: Express | J6: 144 | K6: Product_144 | L6: Electronics | M6: 413.23 | N6: 274.34 | O6: 5 | Q6: 349 | R6: 4
A7: 2095 | B7: Customer_5 | C7: 73 | D7: Giza | E7: 04/02/2021 | F7: 0 | G7: 13623 | H7: 04/02/2021 | I7: Express | J7: 114 | K7: Product_114 | L7: Sports | M7: 562.92 | N7: 253.15 | O7: 2 | Q7: 598 | R7: 3
A8: 2044 | B8: customer_6 | C8: 35 | D8: Mansoura | E8: 10/12/2020 | F8: 1 | G8: 10478 | H8: 10/12/2020 | I8: Same Day | J8: 138 | K8: Product_138 | L8: Clothing | M8: 1122.25 | N8: 537.95 | O8: 1 | Q8: 1542 | R8: 1
A9: 1121 | B9: Customer_7 | C9: -3 | D9: Cairo | E9: 07/28/2020 | F9: 0 | G9: 11422 | H9: 07/28/2020 | I9: Express | J9: 122 | K9: Product_122 | L9: Clothing | M9: 766.64 | N9: 339.98 | O9: 4 | Q9: 448 | R9: 5
A10: 1466 | B10: Customer_8 | C10: 38 | D10: Aswan | E10: 17-10-2023 | F10: 0 | G10: 12481 | H10: 17-10-2023 | I10: Express | J10: 109 | K10: Product_109 | L10: Home Appliances | M10: 91.54 | N10: 39.48 | O10: 1 | P10: 0.1 | Q10: 442 | R10: 4
A11: 2238 | B11: Customer_9 | C11: 56 | D11: Cairo | E11: 01/21/2023 | F11: 0 | G11: 12689 | H11: 01/21/2023 | I11: Same Day | J11: 149 | K11: Product_149 | L11: Sports | M11: 944.43 | N11: 462.86 | O11: 2 | Q11: 356 | R11: 3
A12: 1330 | B12: Customer_10 | C12: 40 | D12: Aswan | E12: 27-06-2020 | F12: 0 | G12: 10692 | H12: 27-06-2020 | I12: Standard | J12: 140 | K12: Product_140 | L12: Electronics | M12: 646.58 | N12: 452.45 | O12: 3 | Q12: 463 | R12: 6
A13: 2482 | B13: customer_11 | C13: 50 | D13: Mansoura | E13: 24-04-2023 | F13: 0 | G13: 13038 | H13: 24-04-2023 | I13: Standard | J13: 126 | K13: Product_126 | L13: Clothing | M13: 1386.66 | N13: 593.9 | O13: 5 | P13: 0.2 | Q13: 618 | R13: 5
A14: 1087 | B14: Customer_12 | C14: 54 | D14: Alexandria | E14: 14-05-2022 | F14: 0 | G14: 12969 | H14: 14-05-2022 | I14: Express | J14: 145 | K14: Product_145 | L14: Home Appliances | M14: 774.37 | N14: 359.23 | O14: 4 | Q14: 460 | R14: 3
A15: 2396 | B15: Customer_13 | C15: 34 | D15: Aswan | E15: 03/06/2020 | F15: 1 | G15: 10193 | H15: 03/06/2020 | I15: Same Day | J15: 105 | K15: Product_105 | L15: Elec | M15: 1078.01 | N15: 519.05 | O15: 1 | Q15: 445 | R15: 3
A16: 2123 | B16: Customer_14 | C16: 32 | D16: Cairo | E16: 02-03-2020 | F16: 1 | G16: 12890 | H16: 02-03-2020 | I16: Express | J16: 129 | K16: Product_129 | L16: Home Appliances | M16: 367.36 | N16: 215.18 | O16: 2 | P16: 0.05 | Q16: 1257 | R16: 5
A17: 1871 | B17: Customer_15 | C17: 42 | D17: Mansoura | E17: 10-07-2020 | F17: 0 | G17: 12848 | H17: 10-07-2020 | I17: Same Day | J17: 122 | K17: Product_122 | L17: Electronics | M17: 1153.41 | N17: 719.27 | O17: 2 | P17: 0.05 | Q17: 346 | R17: 4
A18: 1130 | B18: CUSTOMER_16 | C18: 42 | D18: Cairo | E18: 03/23/2021 | F18: 0 | G18: 11489 | H18: 03/23/2021 | I18: Standard | J18: 149 | K18: Product_149 | L18: Home Appliances | M18: 1095.39 | N18: 685.25 | O18: 5 | P18: 0.05 | Q18: 398 | R18: 4
A19: 2332 | B19: customer_17 | C19: 40 | D19: Alexandria | E19: 21-04-2021 | F19: 0 | G19: 13412 | H19: 21-04-2021 | I19: Standard | J19: 103 | K19: Product_103 | L19: Electronics | M19: 1360.92 | O19: 4 | P19: 0.05 | Q19: 789 | R19: 4
A20: 1769 | B20: Customer_18 | C20: 41 | D20: Giza | E20: 31-10-2022 | F20: 0 | G20: 10058 | H20: 31-10-2022 | I20: Standard | J20: 128 | K20: Product_128 | L20: Sports | M20: 99.04 | N20: 58.98 | O20: 1 | Q20: 654 | R20: 7
A21: 1343 | B21: Customer_19 | C21: 200 | D21: Alexandria | E21: 17-05-2023 | F21: 0 | G21: 11886 | H21: 17-05-2023 | I21: Express | J21: 138 | K21: Product_138 | L21: Elec | M21: 698.88 | O21: 1 | Q21: 595 | R21: 2
A22: 2437 | B22: CUSTOMER_20 | C22: 51 | D22: Luxor | E22: 02/24/2020 | F22: 0 | G22: 13609 | H22: 02/24/2020 | I22: Standard | J22: 114 | K22: Product_114 | L22: Electronics | M22: 1034.78 | N22: 574.61 | O22: 1 | P22: 0.05 | Q22: 432 | R22: 5
A23: 1805 | B23: Customer_21 | C23: 48 | D23: Mansoura | E23: 02/23/2023 | F23: 0 | G23: 10477 | H23: 02/23/2023 | I23: Standard | J23: 147 | K23: Product_147 | L23: Electronics | M23: 187.99 | N23: 96.58 | O23: 5 | Q23: 521 | R23: 4
A24: 1385 | B24: Customer_22 | C24: 19 | D24: Alexandria | E24: 11-02-2021 | F24: 0 | G24: 11126 | H24: 11-02-2021 | I24: Express | J24: 114 | K24: Product_114 | L24: Home Appliances | M24: 645.38 | N24: 412.55 | O24: 5 | Q24: 378 | R24: 6
A25: 2215 | B25: Customer_23 | C25: 34 | D25: Giza | E25: 06-01-2024 | F25: 0 | G25: 12580 | H25: 06-01-2024 | I25: Same Day | J25: 143 | K25: Product_143 | L25: Clothing | M25: 1416.11 | N25: 712.54 | O25: 4 | P25: 0.1 | Q25: 361 | R25: 3
A26: 1955 | B26: Customer_24 | C26: 41 | D26: Cairo | E26: 23-08-2023 | F26: 0 | G26: 11968 | H26: 23-08-2023 | I26: Standard | J26: 111 | K26: Product_111 | L26: Electronics | M26: 682.11 | N26: 319.91 | O26: 1 | P26: 0.05 | Q26: 371 | R26: 6
A27: 1276 | B27: Customer_25 | C27: 31 | D27: Mansoura | E27: 12/07/2023 | F27: 0 | G27: 10591 | H27: 12/07/2023 | I27: Same Day | J27: 109 | K27: Product_109 | L27: Electronics | M27: 1478.84 | N27: 729.11 | O27: 1 | Q27: 391 | R27: 8
A28: 2184 | B28: customer_26 | C28: 49 | D28: Aswan | E28: 21-01-2023 | F28: 0 | G28: 10838 | H28: 21-01-2023 | I28: Same Day | J28: 138 | K28: Product_138 | L28: Sports | M28: 132.42 | N28: 70.43 | O28: 4 | P28: 0.2 | Q28: 338 | R28: 9
A29: 1459 | B29: CUSTOMER_27 | C29: 38 | D29: Alexandria | E29: 09-05-2022 | F29: 0 | G29: 13782 | H29: 09-05-2022 | I29: Express | J29: 147 | K29: Product_147 | L29: Electronics | M29: 1090.85 | N29: 506.39 | O29: 4 | P29: 0.05 | Q29: 338 | R29: 6
A30: 2337 | B30: customer_28 | C30: 42 | D30: Giza | E30: 03/27/2021 | F30: 0 | G30: 11345 | H30: 03/27/2021 | I30: Same Day | J30: 144 | K30: Product_144 | L30: Sports | M30: 892.47 | N30: 519.66 | O30: 4 | P30: 0.2 | Q30: 388 | R30: 7
A31: 1021 | B31: Customer_29 | C31: 33 | D31: Alexandria | E31: 07/08/2022 | F31: 0 | G31: 10548 | H31: 07/08/2022 | I31: Same Day | J31: 106 | K31: Product_106 | L31: Electronics | M31: 775.78 | N31: 516.1 | O31: 2 | P31: 0.2 | Q31: 908 | R31: 6
A32: 1252 | B32: Customer_30 | C32: 10 | D32: Luxor | E32: 04/21/2023 | F32: 0 | G32: 13085 | H32: 04/21/2023 | I32: Express | J32: 101 | K32: Product_101 | L32: Home Appliances | M32: 1457.73 | N32: 843.5 | O32: 4 | Q32: 621 | R32: 4
A33: 1747 | B33: Customer_31 | C33: 9 | D33: Mansoura | E33: 07/23/2021 | F33: 1 | G33: 13527 | H33: 07/23/2021 | I33: Same Day | J33: 125 | K33: Product_125 | L33: Clothing | M33: 237.99 | N33: 127.09 | O33: 3 | P33: 0.05 | Q33: 685 | R33: 4
A34: 1856 | B34: Customer_32 | C34: 48 | D34: Cairo | E34: 14-01-2020 | F34: 1 | G34: 10220 | H34: 14-01-2020 | I34: Standard | J34: 116 | K34: Product_116 | L34: Clothing | M34: 1349.2 | N34: 862.22 | O34: 5 | Q34: 1565 | R34: 2
A35: 1474 | B35: customer_33 | C35: 44 | D35: Giza | E35: 22-11-2020 | F35: 1 | G35: 10875 | H35: 22-11-2020 | I35: Express | J35: 115 | K35: Product_115 | L35: Clothing | M35: 1052.3 | N35: 657.07 | O35: 4 | P35: 0.1 | Q35: 1501 | R35: 3
A36: 2082 | B36: Customer_34 | C36: 46 | D36: Alexandria | E36: 11/30/2023 | F36: 0 | G36: 13462 | H36: 11/30/2023 | I36: Express | J36: 134 | K36: Product_134 | L36: Home Appliances | M36: 425.54 | N36: 217.08 | O36: 2 | P36: 0.05 | Q36: 398 | R36: 8
A37: 1510 | B37: customer_35 | C37: 42 | D37: Mansoura | E37: 05/15/2022 | F37: 0 | G37: 12725 | H37: 05/15/2022 | I37: Express | J37: 117 | K37: Product_117 | L37: Sports | M37: 1357.42 | N37: 789 | O37: 3 | Q37: 532 | R37: 5
A38: 2499 | B38: Customer_36 | C38: 43 | D38: Alexandria | E38: 27-11-2021 | F38: 0 | G38: 11196 | H38: 27-11-2021 | I38: Standard | J38: 103 | K38: Product_103 | L38: Clothing | M38: 672.48 | N38: 416.23 | O38: 2 | Q38: 440 | R38: 4
A39: 1699 | B39: Customer_37 | C39: 54 | D39: Mansoura | E39: 23-07-2021 | F39: 0 | G39: 12709 | H39: 23-07-2021 | I39: Same Day | J39: 103 | K39: Product_103 | L39: Home Appliances | M39: 1230.63 | N39: 582.87 | O39: 2 | Q39: 433 | R39: 9
A40: 1975 | B40: CUSTOMER_38 | C40: 46 | D40: Luxor | E40: 11/14/2020 | F40: 1 | G40: 12731 | H40: 11/14/2020 | I40: Same Day | J40: 137 | K40: Product_137 | L40: Home Appliances | M40: 613.81 | N40: 312.97 | O40: 2 | P40: 0.1 | Q40: 1509 | R40: 2
A41: 1189 | B41: Customer_39 | C41: 55 | D41: Alexandria | E41: 16-03-2021 | F41: 0 | G41: 13152 | H41: 16-03-2021 | I41: Same Day | J41: 117 | K41: Product_117 | L41: Elec | M41: 1283.85 | N41: 554.28 | O41: 2 | P41: 0.1 | Q41: 580 | R41: 6
A42: 1957 | B42: Customer_40 | C42: 42 | D42: Luxor | E42: 20-11-2021 | F42: 0 | G42: 10335 | H42: 20-11-2021 | I42: Standard | J42: 149 | K42: Product_149 | L42: Sports | M42: 973.11 | N42: 677.58 | O42: 1 | Q42: 390 | R42: 7
A43: 1686 | B43: Customer_41 | C43: 35 | D43: Aswan | E43: 07/28/2020 | F43: 0 | G43: 10224 | H43: 07/28/2020 | I43: Same Day | J43: 138 | K43: Product_138 | L43: Home Appliances | M43: 254.52 | N43: 108.37 | O43: 5 | Q43: 531 | R43: 4
A44: 1957 | B44: Customer_42 | C44: 42 | D44: Aswan | E44: 08-07-2020 | F44: 0 | G44: 12918 | H44: 08-07-2020 | I44: Same Day | J44: 101 | K44: Product_101 | L44: Sports | M44: 992.01 | N44: 446.98 | O44: 1 | P44: 0.1 | Q44: 390 | R44: 7
A45: 1562 | B45: customer_43 | C45: 27 | D45: Giza | E45: 17-02-2022 | F45: 1 | G45: 12082 | H45: 17-02-2022 | I45: Standard | J45: 107 | K45: Product_107 | L45: Clothing | M45: 327.45 | N45: 178.12 | O45: 3 | Q45: 1049 | R45: 6
A46: 2267 | B46: Customer_44 | C46: 34 | D46: Luxor | E46: 07/17/2020 | F46: 1 | G46: 13941 | H46: 07/17/2020 | I46: Standard | J46: 126 | K46: Product_126 | L46: Clothing | M46: 647.29 | N46: 426.94 | O46: 1 | Q46: 919 | R46: 2
A47: 1831 | B47: CUSTOMER_45 | C47: 42 | D47: Mansoura | E47: 05-01-2022 | F47: 1 | G47: 10187 | H47: 05-01-2022 | I47: Same Day | J47: 147 | K47: Product_147 | L47: Clothing | M47: 296.93 | N47: 150.47 | O47: 3 | Q47: 1092 | R47: 2
A48: 2154 | B48: Customer_46 | C48: 42 | D48: Giza | E48: 05-12-2021 | F48: 1 | G48: 11247 | H48: 05-12-2021 | I48: Standard | J48: 139 | K48: Product_139 | L48: Electronics | M48: 81.92 | N48: 51.66 | O48: 4 | P48: 0.2 | Q48: 1123 | R48: 4
A49: 1646 | B49: Customer_47 | C49: 38 | D49: Alexandria | E49: 21-05-2023 | F49: 0 | G49: 12690 | H49: 21-05-2023 | I49: Standard | J49: 119 | K49: Product_119 | L49: Electronics | M49: 357.24 | N49: 215.35 | O49: 3 | P49: 0.05 | Q49: 591 | R49: 3
A50: 1020 | B50: Customer_48 | C50: 19 | D50: Alexandria | E50: 25-06-2021 | F50: 0 | G50: 13957 | H50: 25-06-2021 | I50: Standard | J50: 130 | K50: Product_130 | L50: Sports | M50: 827.74 | N50: 489.69 | O50: 1 | Q50: 534 | R50: 7
A51: 1840 | B51: Customer_49 | C51: 49 | D51: Mansoura | E51: 03/29/2020 | F51: 1 | G51: 10962 | H51: 03/29/2020 | I51: Express | J51: 143 | K51: Product_143 | L51: Sports | M51: 748.26 | N51: 488.99 | O51: 1 | Q51: 1047 | R51: 2
A52: 1166 | B52: Customer_50 | C52: 52 | D52: Cairo | E52: 03-02-2024 | F52: 0 | G52: 13015 | H52: 03-02-2024 | I52: Express | J52: 114 | K52: Product_114 | L52: Electronics | M52: 777.17 | N52: 314.17 | O52: 3 | Q52: 333 | R52: 3
A53: 2297 | B53: Customer_51 | C53: 64 | D53: Cairo | E53: 29-07-2022 | F53: 0 | G53: 10493 | H53: 29-07-2022 | I53: Same Day | J53: 113 | K53: Product_113 | L53: Home Appliances | M53: 409.15 | N53: 277.71 | O53: 1 | P53: 0.1 | Q53: 887 | R53: 3
A54: 1387 | B54: Customer_52 | C54: 46 | D54: Alexandria | E54: 03-01-2023 | F54: 1 | G54: 11886 | H54: 03-01-2023 | I54: Same Day | J54: 120 | K54: Product_120 | L54: Sports | M54: 1043.48 | N54: 676.98 | O54: 3 | Q54: 622 | R54: 2
A55: 1600 | B55: Customer_53 | C55: 40 | D55: Mansoura | E55: 12-09-2020 | F55: 1 | G55: 10310 | H55: 12-09-2020 | I55: Standard | J55: 126 | K55: Product_126 | L55: Sports | M55: 1071.18 | N55: 729.86 | O55: 2 | Q55: 1115 | R55: 4
A56: 1315 | B56: CUSTOMER_54 | C56: 24 | D56: Cairo | E56: 14-02-2022 | F56: 1 | G56: 12568 | H56: 14-02-2022 | I56: Same Day | J56: 127 | K56: Product_127 | L56: Clothing | M56: 569.05 | N56: 363.1 | O56: 5 | Q56: 1052 | R56: 1
A57: 1013 | B57: Customer_55 | C57: 62 | D57: Luxor | E57: 10-06-2020 | F57: 0 | G57: 11604 | H57: 10-06-2020 | I57: Express | J57: 125 | K57: Product_125 | L57: Sports | M57: 1327.7 | N57: 881.03 | O57: 3 | P57: 0.2 | Q57: 867 | R57: 3
A58: 1241 | B58: customer_56 | C58: 43 | D58: Alexandria | E58: 02/04/2023 | F58: 0 | G58: 11563 | H58: 02/04/2023 | I58: Same Day | J58: 109 | K58: Product_109 | L58: Sports | M58: 983.83 | N58: 453.47 | O58: 2 | Q58: 482 | R58: 7
A59: 1776 | B59: Customer_57 | C59: 42 | D59: Aswan | E59: 23-08-2021 | F59: 1 | G59: 13982 | H59: 23-08-2021 | I59: Same Day | J59: 141 | K59: Product_141 | L59: Home Appliances | M59: 1083.91 | N59: 537.37 | O59: 2 | Q59: 603 | R59: 2
A60: 2369 | B60: CUSTOMER_58 | C60: 36 | D60: Luxor | E60: 11-07-2023 | F60: 1 | G60: 10368 | H60: 11-07-2023 | I60: Express | J60: 148 | K60: Product_148 | L60: Sports | M60: 452.14 | N60: 223.61 | O60: 2 | P60: 0.1 | Q60: 540 | R60: 4
A61: 1564 | B61: Customer_59 | C61: 35 | D61: Mansoura | E61: 20-06-2023 | F61: 0 | G61: 13546 | H61: 20-06-2023 | I61: Express | J61: 112 | K61: Product_112 | L61: Home Appliances | M61: 50.89 | N61: 22.02 | O61: 2 | P61: 0.2 | Q61: 561 | R61: 2
A62: 1897 | B62: Customer_60 | C62: 50 | D62: Aswan | E62: 10-01-2022 | F62: 1 | G62: 10745 | H62: 10-01-2022 | I62: Standard | J62: 110 | K62: Product_110 | L62: Clothing | M62: 1304.79 | N62: 807.5 | O62: 3 | Q62: 1003 | R62: 4
A63: 2363 | B63: Customer_61 | C63: 24 | D63: Luxor | E63: 28-03-2023 | F63: 0 | G63: 12078 | H63: 28-03-2023 | I63: Standard | J63: 106 | K63: Product_106 | L63: Electronics | M63: 1242.52 | N63: 547.77 | O63: 1 | Q63: 645 | R63: 4
A64: 1091 | B64: Customer_62 | C64: 64 | D64: Cairo | E64: 28-01-2021 | F64: 0 | G64: 13898 | H64: 28-01-2021 | I64: Standard | J64: 134 | K64: Product_134 | L64: Clothing | M64: 228.63 | N64: 95.05 | O64: 2 | Q64: 551 | R64: 6
A65: 2390 | B65: CUSTOMER_63 | C65: 61 | D65: Cairo | E65: 13-12-2023 | F65: 0 | G65: 11255 | H65: 13-12-2023 | I65: Same Day | J65: 141 | K65: Product_141 | L65: Home Appliances | M65: 592.45 | N65: 374.8 | O65: 4 | Q65: 385 | R65: 5
A66: 1955 | B66: Customer_64 | C66: 34 | D66: Aswan | E66: 22-05-2020 | F66: 0 | G66: 13921 | H66: 22-05-2020 | I66: Same Day | J66: 119 | K66: Product_119 | L66: Home Appliances | M66: 1008.94 | N66: 677.4 | O66: 2 | Q66: 371 | R66: 6
A67: 2478 | B67: Customer_65 | C67: 27 | D67: Giza | E67: 03-04-2020 | F67: 0 | G67: 10997 | H67: 03-04-2020 | I67: Same Day | J67: 106 | K67: Product_106 | L67: Sports | M67: 995.56 | N67: 626.44 | O67: 1 | Q67: 653 | R67: 5
A68: 2451 | B68: customer_66 | C68: 9 | D68: Alexandria | E68: 16-09-2023 | F68: 0 | G68: 10496 | H68: 16-09-2023 | I68: Express | J68: 102 | K68: Product_102 | L68: Sports | M68: 1297.51 | N68: 840.27 | O68: 1 | Q68: 403 | R68: 3
A69: 1508 | B69: Customer_67 | C69: 21 | D69: Aswan | E69: 11-04-2021 | F69: 0 | G69: 11589 | H69: 11-04-2021 | I69: Same Day | J69: 115 | K69: Product_115 | L69: elect | M69: 253.39 | N69: 146.63 | O69: 5 | P69: 0.1 | Q69: 428 | R69: 6
A70: 1775 | B70: Customer_68 | C70: 50 | D70: Mansoura | E70: 08/15/2021 | F70: 0 | G70: 10963 | H70: 08/15/2021 | I70: Express | J70: 117 | K70: Product_117 | L70: Home Appliances | M70: 673.41 | N70: 448.71 | O70: 5 | Q70: 454 | R70: 7
A71: 1034 | B71: Customer_69 | C71: 44 | D71: Alexandria | E71: 06/12/2020 | F71: 0 | G71: 12004 | H71: 06/12/2020 | I71: Same Day | J71: 116 | K71: Product_116 | L71: Home Appliances | M71: 190.98 | N71: 104.85 | O71: 2 | Q71: 763 | R71: 3
A72: 1205 | B72: CUSTOMER_70 | C72: 47 | D72: Luxor | E72: 21-04-2021 | F72: 0 | G72: 11198 | H72: 21-04-2021 | I72: Same Day | J72: 128 | K72: Product_128 | L72: Clothing | M72: 614.91 | N72: 428.28 | O72: 2 | Q72: 417 | R72: 5
A73: 2104 | B73: Customer_71 | C73: 12 | D73: Mansoura | E73: 25-07-2020 | F73: 1 | G73: 12345 | H73: 25-07-2020 | I73: Express | J73: 121 | K73: Product_121 | L73: Elec | M73: 71.91 | N73: 30.99 | O73: 5 | Q73: 735 | R73: 5
A74: 2411 | B74: CUSTOMER_72 | C74: 34 | D74: Mansoura | E74: 17-02-2022 | F74: 0 | G74: 11814 | H74: 17-02-2022 | I74: Express | J74: 108 | K74: Product_108 | L74: Clothing | M74: 1352.5 | N74: 869.33 | O74: 2 | Q74: 1049 | R74: 2
A75: 2025 | B75: Customer_73 | C75: 60 | D75: Cairo | E75: 07/23/2021 | F75: 1 | G75: 11388 | H75: 07/23/2021 | I75: Express | J75: 110 | K75: Product_110 | L75: Sports | M75: 814.21 | N75: 482.35 | O75: 4 | P75: 0.1 | Q75: 1258 | R75: 1
A76: 2021 | B76: customer_74 | C76: 38 | D76: Luxor | E76: 07/17/2022 | F76: 0 | G76: 11109 | H76: 07/17/2022 | I76: Standard | J76: 110 | K76: Product_110 | L76: Sports | M76: 1282.21 | N76: 736.24 | O76: 3 | Q76: 457 | R76: 4
A77: 2413 | B77: Customer_75 | C77: 20 | D77: Cairo | E77: 07/25/2023 | F77: 0 | G77: 10576 | H77: 07/25/2023 | I77: Standard | J77: 110 | K77: Product_110 | L77: Clothing | M77: 136.86 | N77: 84.54 | O77: 5 | P77: 0.05 | Q77: 526 | R77: 4
A78: 1565 | B78: Customer_76 | C78: 38 | D78: Cairo | E78: 01/17/2022 | F78: 1 | G78: 13160 | H78: 01/17/2022 | I78: Same Day | J78: 109 | K78: Product_109 | L78: Sports | M78: 379.81 | N78: 247.67 | O78: 5 | Q78: 914 | R78: 4
A79: 2129 | B79: Customer_77 | C79: 28 | D79: Giza | E79: 29-11-2020 | F79: 0 | G79: 10053 | H79: 29-11-2020 | I79: Same Day | J79: 128 | K79: Product_128 | L79: Clothing | M79: 426.1 | N79: 280.74 | O79: 1 | Q79: 459 | R79: 4
A80: 1702 | B80: Customer_78 | C80: 45 | D80: Cairo | E80: 01/28/2022 | F80: 1 | G80: 13701 | H80: 01/28/2022 | I80: Same Day | J80: 124 | K80: Product_124 | L80: Home Appliances | M80: 610.7 | N80: 276.41 | O80: 2 | Q80: 387 | R80: 5
A81: 1401 | B81: Customer_79 | C81: 40 | D81: Alexandria | E81: 28-12-2021 | F81: 1 | G81: 13432 | H81: 28-12-2021 | I81: Standard | J81: 119 | K81: Product_119 | L81: Home Appliances | M81: 1214.16 | N81: 557.43 | O81: 5 | Q81: 1100 | R81: 3
A82: 1729 | B82: Customer_80 | C82: 48 | D82: Mansoura | E82: 05-03-2021 | F82: 0 | G82: 13547 | H82: 05-03-2021 | I82: Same Day | J82: 133 | K82: Product_133 | L82: Sports | M82: 610.51 | N82: 247.16 | O82: 5 | P82: 0.1 | Q82: 592 | R82: 3
A83: 1161 | B83: Customer_81 | C83: 21 | D83: Cairo | E83: 10/04/2023 | F83: 0 | G83: 10228 | H83: 10/04/2023 | I83: Express | J83: 104 | K83: Product_104 | L83: Electronics | M83: 346.75 | N83: 152.41 | O83: 4 | P83: 0.1 | Q83: 455 | R83: 6
A84: 1201 | B84: Customer_82 | C84: 33 | D84: Aswan | E84: 06/30/2021 | F84: 0 | G84: 10778 | H84: 06/30/2021 | I84: Express | J84: 103 | K84: Product_103 | L84: Home Appliances | M84: 144.24 | N84: 69.11 | O84: 2 | Q84: 765 | R84: 5
A85: 1995 | B85: Customer_83 | C85: 56 | D85: Alexandria | E85: 12/08/2023 | F85: 0 | G85: 13902 | H85: 12/08/2023 | I85: Standard | J85: 142 | K85: Product_142 | L85: Sports | M85: 165.26 | N85: 101.85 | O85: 3 | Q85: 390 | R85: 2
A86: 1269 | B86: Customer_84 | C86: 19 | D86: Luxor | E86: 10/31/2023 | F86: 0 | G86: 11557 | H86: 10/31/2023 | I86: Express | J86: 112 | K86: Product_112 | L86: Electronics | M86: 1152.07 | N86: 625.26 | O86: 4 | Q86: 428 | R86: 5
A87: 1815 | B87: Customer_85 | C87: 24 | D87: Mansoura | E87: 20-08-2023 | F87: 1 | G87: 13830 | H87: 20-08-2023 | I87: Express | J87: 118 | K87: Product_118 | L87: Sports | M87: 694.96 | N87: 436 | O87: 3 | P87: 0.2 | Q87: 439 | R87: 6
A88: 2294 | B88: Customer_86 | C88: 42 | D88: Aswan | E88: 26-05-2020 | F88: 0 | G88: 10984 | H88: 26-05-2020 | I88: Same Day | J88: 123 | K88: Product_123 | L88: Clothing | M88: 1102.96 | N88: 602.17 | O88: 1 | Q88: 673 | R88: 5
A89: 1455 | B89: customer_87 | C89: 44 | D89: Aswan | E89: 06/01/2023 | F89: 0 | G89: 10372 | H89: 06/01/2023 | I89: Express | J89: 120 | K89: Product_120 | L89: Sports | M89: 1039.32 | N89: 588.96 | O89: 5 | Q89: 347 | R89: 6
A90: 2485 | B90: Customer_88 | C90: 32 | D90: Luxor | E90: 07/24/2023 | F90: 0 | G90: 10468 | H90: 07/24/2023 | I90: Express | J90: 106 | K90: Product_106 | L90: Clothing | M90: 246.28 | O90: 4 | Q90: 527 | R90: 4
A91: 2275 | B91: Customer_89 | C91: 35 | D91: Aswan | E91: 16-12-2020 | F91: 0 | G91: 12467 | H91: 16-12-2020 | I91: Standard | J91: 134 | K91: Product_134 | L91: Home Appliances | M91: 257.19 | N91: 162.79 | O91: 3 | Q91: 552 | R91: 5
A92: 2016 | B92: Customer_90 | C92: 47 | D92: Alexandria | E92: 29-12-2022 | F92: 0 | G92: 11849 | H92: 29-12-2022 | I92: Express | J92: 142 | K92: Product_142 | L92: Home Appliances | M92: 1145.25 | N92: 718.57 | O92: 2 | Q92: 478 | R92: 6
A93: 1295 | B93: Customer_91 | C93: 52 | D93: Luxor | E93: 02-02-2024 | F93: 0 | G93: 10531 | H93: 02-02-2024 | I93: Express | J93: 102 | K93: Product_102 | L93: Sports | M93: 1095.84 | N93: 539.45 | O93: 1 | Q93: 334 | R93: 5
A94: 1719 | B94: Customer_92 | C94: 23 | D94: Aswan | E94: 05/16/2021 | F94: 0 | G94: 11423 | H94: 05/16/2021 | I94: Same Day | J94: 130 | K94: Product_130 | L94: Electronics | M94: 598.14 | N94: 298.22 | O94: 1 | Q94: 650 | R94: 4
A95: 1337 | B95: Customer_93 | C95: 45 | D95: Luxor | E95: 11/30/2020 | F95: 0 | G95: 13035 | H95: 11/30/2020 | I95: Same Day | J95: 109 | K95: Product_109 | L95: Sports | M95: 162.26 | N95: 75.6 | O95: 5 | Q95: 352 | R95: 8
A96: 1878 | B96: Customer_94 | C96: 62 | D96: Luxor | E96: 04-08-2022 | F96: 1 | G96: 11207 | H96: 04-08-2022 | I96: Same Day | J96: 127 | K96: Product_127 | L96: Sports | M96: 67.54 | N96: 43.51 | O96: 5 | Q96: 881 | R96: 3
A97: 2076 | B97: Customer_95 | C97: 38 | D97: Cairo | E97: 02/16/2022 | F97: 0 | G97: 13932 | H97: 02/16/2022 | I97: Standard | J97: 142 | K97: Product_142 | L97: Home Appliances | M97: 467.83 | N97: 291.97 | O97: 3 | Q97: 827 | R97: 6
A98: 1791 | B98: customer_96 | C98: 23 | D98: Cairo | E98: 07/06/2021 | F98: 1 | G98: 10561 | H98: 07/06/2021 | I98: Same Day | J98: 134 | K98: Product_134 | L98: Home Appliances | M98: 63.37 | N98: 36.93 | O98: 3 | Q98: 648 | R98: 4
A99: 1216 | B99: Customer_97 | C99: 23 | D99: Cairo | E99: 03-08-2023 | F99: 0 | G99: 10089 | H99: 03-08-2023 | I99: Express | J99: 140 | K99: Product_140 | L99: Sports | M99: 383.61 | N99: 180.93 | O99: 1 | Q99: 517 | R99: 5
A100: 1763 | B100: CUSTOMER_98 | C100: 37 | D100: Aswan | E100: 11/10/2023 | F100: 0 | G100: 11639 | H100: 11/10/2023 | I100: Standard | J100: 124 | K100: Product_124 | L100: Home Appliances | M100: 658.28 | O100: 3 | Q100: 403 | R100: 5
...

Sheet 2. Cleaned Data
A1: CustomerID | B1: FullName | C1: Age | D1: City | E1: JoinDate | F1: Churn | G1: OrderID | H1: OrderDate | I1: ShipMode | J1: ProductID | K1: ProductName | L1: Category | M1: Price | N1: Cost | O1: Quantity | P1: Discount | Q1: Days_Since_Last_Order | R1: Total_Orders | S1: Revenue | T1: Profit | U1: Profit Margin %
A2: 2126 | B2: =PROPER(TRIM('1. Raw Data'!B2)) -> Customer_0 | C2: =IF(OR('1. Raw Data'!C2<18, '1. Raw Data'!C2>100), MEDIAN('1. Raw Data'!$C$2:$C$5001), '1. Raw Data'!C2) -> 35 | D2: Mansoura | E2: 44965 | F2: 0 | G2: 11420 | H2: 45140 | I2: Same Day | J2: 135 | K2: Product_135 | L2: =IF(OR('1. Raw Data'!L2="Elec", '1. Raw Data'!L2="elect"), "Electronics", '1. Raw Data'!L2) -> Home Appliances | M2: 712.82 | N2: =IF(ISBLANK('1. Raw Data'!N2), MEDIAN('1. Raw Data'!$N$2:$N$5001), '1. Raw Data'!N2) -> 334.36 | O2: 1 | P2: =IF(ISBLANK('1. Raw Data'!P2), 0, '1. Raw Data'!P2) -> 0 | Q2: 518 | R2: 4 | S2: =M2 * O2 * (1 - P2) -> 712.82 | T2: =S2 - (N2 * O2) -> 378.46 | U2: =T2 / S2 -> 0.53093348
A3: 2459 | B3: =PROPER(TRIM('1. Raw Data'!B3)) -> Customer_1 | C3: =IF(OR('1. Raw Data'!C3<18, '1. Raw Data'!C3>100), MEDIAN('1. Raw Data'!$C$2:$C$5001), '1. Raw Data'!C3) -> 54 | D3: Cairo | E3: 44059 | F3: 0 | G3: 12597 | H3: 44059 | I3: Express | J3: 119 | K3: Product_119 | L3: =IF(OR('1. Raw Data'!L3="Elec", '1. Raw Data'!L3="elect"), "Electronics", '1. Raw Data'!L3) -> Home Appliances | M3: 148.6 | N3: =IF(ISBLANK('1. Raw Data'!N3), MEDIAN('1. Raw Data'!$N$2:$N$5001), '1. Raw Data'!N3) -> 76.56 | O3: 2 | P3: =IF(ISBLANK('1. Raw Data'!P3), 0, '1. Raw Data'!P3) -> 0.05 | Q3: 661 | R3: 6 | S3: =M3 * O3 * (1 - P3) -> 282.34 | T3: =S3 - (N3 * O3) -> 129.22 | U3: =T3 / S3 -> 0.45767514
A4: 1860 | B4: =PROPER(TRIM('1. Raw Data'!B4)) -> Customer_2 | C4: =IF(OR('1. Raw Data'!C4<18, '1. Raw Data'!C4>100), MEDIAN('1. Raw Data'!$C$2:$C$5001), '1. Raw Data'!C4) -> 60 | D4: Mansoura | E4: 43882 | F4: 1 | G4: 10496 | H4: 43882 | I4: Same Day | J4: 113 | K4: Product_113 | L4: =IF(OR('1. Raw Data'!L4="Elec", '1. Raw Data'!L4="elect"), "Electronics", '1. Raw Data'!L4) -> Clothing | M4: 1039.74 | N4: =IF(ISBLANK('1. Raw Data'!N4), MEDIAN('1. Raw Data'!$N$2:$N$5001), '1. Raw Data'!N4) -> 640.86 | O4: 1 | P4: =IF(ISBLANK('1. Raw Data'!P4), 0, '1. Raw Data'!P4) -> 0.05 | Q4: 1094 | R4: 3 | S4: =M4 * O4 * (1 - P4) -> 987.753 | T4: =S4 - (N4 * O4) -> 346.893 | U4: =T4 / S4 -> 0.35119407
A5: 2294 | B5: =PROPER(TRIM('1. Raw Data'!B5)) -> Customer_3 | C5: =IF(OR('1. Raw Data'!C5<18, '1. Raw Data'!C5>100), MEDIAN('1. Raw Data'!$C$2:$C$5001), '1. Raw Data'!C5) -> 40 | D5: Cairo | E5: 44394 | F5: 0 | G5: 12220 | H5: 44394 | I5: Same Day | J5: 105 | K5: Product_105 | L5: =IF(OR('1. Raw Data'!L5="Elec", '1. Raw Data'!L5="elect"), "Electronics", '1. Raw Data'!L5) -> Electronics | M5: 117.63 | N5: =IF(ISBLANK('1. Raw Data'!N5), MEDIAN('1. Raw Data'!$N$2:$N$5001), '1. Raw Data'!N5) -> 57.56 | O5: 3 | P5: =IF(ISBLANK('1. Raw Data'!P5), 0, '1. Raw Data'!P5) -> 0 | Q5: 673 | R5: 5 | S5: =M5 * O5 * (1 - P5) -> 352.89 | T5: =S5 - (N5 * O5) -> 180.21 | U5: =T5 / S5 -> 0.51066905
A6: 2130 | B6: =PROPER(TRIM('1. Raw Data'!B6)) -> Customer_4 | C6: =IF(OR('1. Raw Data'!C6<18, '1. Raw Data'!C6>100), MEDIAN('1. Raw Data'!$C$2:$C$5001), '1. Raw Data'!C6) -> 32 | D6: Luxor | E6: 44332 | F6: 0 | G6: 10104 | H6: 44332 | I6: Express | J6: 144 | K6: Product_144 | L6: =IF(OR('1. Raw Data'!L6="Elec", '1. Raw Data'!L6="elect"), "Electronics", '1. Raw Data'!L6) -> Electronics | M6: 413.23 | N6: =IF(ISBLANK('1. Raw Data'!N6), MEDIAN('1. Raw Data'!$N$2:$N$5001), '1. Raw Data'!N6) -> 274.34 | O6: 5 | P6: =IF(ISBLANK('1. Raw Data'!P6), 0, '1. Raw Data'!P6) -> 0 | Q6: 349 | R6: 4 | S6: =M6 * O6 * (1 - P6) -> 2066.15 | T6: =S6 - (N6 * O6) -> 694.45 | U6: =T6 / S6 -> 0.33610822
A7: 2095 | B7: =PROPER(TRIM('1. Raw Data'!B7)) -> Customer_5 | C7: =IF(OR('1. Raw Data'!C7<18, '1. Raw Data'!C7>100), MEDIAN('1. Raw Data'!$C$2:$C$5001), '1. Raw Data'!C7) -> 73 | D7: Giza | E7: 44288 | F7: 0 | G7: 13623 | H7: 44231 | I7: Express | J7: 114 | K7: Product_114 | L7: =IF(OR('1. Raw Data'!L7="Elec", '1. Raw Data'!L7="elect"), "Electronics", '1. Raw Data'!L7) -> Sports | M7: 562.92 | N7: =IF(ISBLANK('1. Raw Data'!N7), MEDIAN('1. Raw Data'!$N$2:$N$5001), '1. Raw Data'!N7) -> 253.15 | O7: 2 | P7: =IF(ISBLANK('1. Raw Data'!P7), 0, '1. Raw Data'!P7) -> 0 | Q7: 598 | R7: 3 | S7: =M7 * O7 * (1 - P7) -> 1125.84 | T7: =S7 - (N7 * O7) -> 619.54 | U7: =T7 / S7 -> 0.55029134
A8: 2044 | B8: =PROPER(TRIM('1. Raw Data'!B8)) -> Customer_6 | C8: =IF(OR('1. Raw Data'!C8<18, '1. Raw Data'!C8>100), MEDIAN('1. Raw Data'!$C$2:$C$5001), '1. Raw Data'!C8) -> 35 | D8: Mansoura | E8: 44116 | F8: 1 | G8: 10478 | H8: 44175 | I8: Same Day | J8: 138 | K8: Product_138 | L8: =IF(OR('1. Raw Data'!L8="Elec", '1. Raw Data'!L8="elect"), "Electronics", '1. Raw Data'!L8) -> Clothing | M8: 1122.25 | N8: =IF(ISBLANK('1. Raw Data'!N8), MEDIAN('1. Raw Data'!$N$2:$N$5001), '1. Raw Data'!N8) -> 537.95 | O8: 1 | P8: =IF(ISBLANK('1. Raw Data'!P8), 0, '1. Raw Data'!P8) -> 0 | Q8: 1542 | R8: 1 | S8: =M8 * O8 * (1 - P8) -> 1122.25 | T8: =S8 - (N8 * O8) -> 584.3 | U8: =T8 / S8 -> 0.52065048
A9: 1121 | B9: =PROPER(TRIM('1. Raw Data'!B9)) -> Customer_7 | C9: =IF(OR('1. Raw Data'!C9<18, '1. Raw Data'!C9>100), MEDIAN('1. Raw Data'!$C$2:$C$5001), '1. Raw Data'!C9) -> 40 | D9: Cairo | E9: 44040 | F9: 0 | G9: 11422 | H9: 44040 | I9: Express | J9: 122 | K9: Product_122 | L9: =IF(OR('1. Raw Data'!L9="Elec", '1. Raw Data'!L9="elect"), "Electronics", '1. Raw Data'!L9) -> Clothing | M9: 766.64 | N9: =IF(ISBLANK('1. Raw Data'!N9), MEDIAN('1. Raw Data'!$N$2:$N$5001), '1. Raw Data'!N9) -> 339.98 | O9: 4 | P9: =IF(ISBLANK('1. Raw Data'!P9), 0, '1. Raw Data'!P9) -> 0 | Q9: 448 | R9: 5 | S9: =M9 * O9 * (1 - P9) -> 3066.56 | T9: =S9 - (N9 * O9) -> 1706.64 | U9: =T9 / S9 -> 0.5565324
A10: 1466 | B10: =PROPER(TRIM('1. Raw Data'!B10)) -> Customer_8 | C10: =IF(OR('1. Raw Data'!C10<18, '1. Raw Data'!C10>100), MEDIAN('1. Raw Data'!$C$2:$C$5001), '1. Raw Data'!C10) -> 38 | D10: Aswan | E10: 45216 | F10: 0 | G10: 12481 | H10: 45216 | I10: Express | J10: 109 | K10: Product_109 | L10: =IF(OR('1. Raw Data'!L10="Elec", '1. Raw Data'!L10="elect"), "Electronics", '1. Raw Data'!L10) -> Home Appliances | M10: 91.54 | N10: =IF(ISBLANK('1. Raw Data'!N10), MEDIAN('1. Raw Data'!$N$2:$N$5001), '1. Raw Data'!N10) -> 39.48 | O10: 1 | P10: =IF(ISBLANK('1. Raw Data'!P10), 0, '1. Raw Data'!P10) -> 0.1 | Q10: 442 | R10: 4 | S10: =M10 * O10 * (1 - P10) -> 82.386 | T10: =S10 - (N10 * O10) -> 42.906 | U10: =T10 / S10 -> 0.52079237
A11: 2238 | B11: =PROPER(TRIM('1. Raw Data'!B11)) -> Customer_9 | C11: =IF(OR('1. Raw Data'!C11<18, '1. Raw Data'!C11>100), MEDIAN('1. Raw Data'!$C$2:$C$5001), '1. Raw Data'!C11) -> 56 | D11: Cairo | E11: 44947 | F11: 0 | G11: 12689 | H11: 44947 | I11: Same Day | J11: 149 | K11: Product_149 | L11: =IF(OR('1. Raw Data'!L11="Elec", '1. Raw Data'!L11="elect"), "Electronics", '1. Raw Data'!L11) -> Sports | M11: 944.43 | N11: =IF(ISBLANK('1. Raw Data'!N11), MEDIAN('1. Raw Data'!$N$2:$N$5001), '1. Raw Data'!N11) -> 462.86 | O11: 2 | P11: =IF(ISBLANK('1. Raw Data'!P11), 0, '1. Raw Data'!P11) -> 0 | Q11: 356 | R11: 3 | S11: =M11 * O11 * (1 - P11) -> 1888.86 | T11: =S11 - (N11 * O11) -> 963.14 | U11: =T11 / S11 -> 0.50990545
A12: 1330 | B12: =PROPER(TRIM('1. Raw Data'!B12)) -> Customer_10 | C12: =IF(OR('1. Raw Data'!C12<18, '1. Raw Data'!C12>100), MEDIAN('1. Raw Data'!$C$2:$C$5001), '1. Raw Data'!C12) -> 40 | D12: Aswan | E12: 44009 | F12: 0 | G12: 10692 | H12: 44009 | I12: Standard | J12: 140 | K12: Product_140 | L12: =IF(OR('1. Raw Data'!L12="Elec", '1. Raw Data'!L12="elect"), "Electronics", '1. Raw Data'!L12) -> Electronics | M12: 646.58 | N12: =IF(ISBLANK('1. Raw Data'!N12), MEDIAN('1. Raw Data'!$N$2:$N$5001), '1. Raw Data'!N12) -> 452.45 | O12: 3 | P12: =IF(ISBLANK('1. Raw Data'!P12), 0, '1. Raw Data'!P12) -> 0 | Q12: 463 | R12: 6 | S12: =M12 * O12 * (1 - P12) -> 1939.74 | T12: =S12 - (N12 * O12) -> 582.39 | U12: =T12 / S12 -> 0.30024127
A13: 2482 | B13: =PROPER(TRIM('1. Raw Data'!B13)) -> Customer_11 | C13: =IF(OR('1. Raw Data'!C13<18, '1. Raw Data'!C13>100), MEDIAN('1. Raw Data'!$C$2:$C$5001), '1. Raw Data'!C13) -> 50 | D13: Mansoura | E13: 45040 | F13: 0 | G13: 13038 | H13: 45040 | I13: Standard | J13: 126 | K13: Product_126 | L13: =IF(OR('1. Raw Data'!L13="Elec", '1. Raw Data'!L13="elect"), "Electronics", '1. Raw Data'!L13) -> Clothing | M13: 1386.66 | N13: =IF(ISBLANK('1. Raw Data'!N13), MEDIAN('1. Raw Data'!$N$2:$N$5001), '1. Raw Data'!N13) -> 593.9 | O13: 5 | P13: =IF(ISBLANK('1. Raw Data'!P13), 0, '1. Raw Data'!P13) -> 0.2 | Q13: 618 | R13: 5 | S13: =M13 * O13 * (1 - P13) -> 5546.64 | T13: =S13 - (N13 * O13) -> 2577.14 | U13: =T13 / S13 -> 0.46463084
... A5001: 1210 | B5001: =PROPER(TRIM('1. Raw Data'!B5001)) -> Customer_4999 | C5001: =IF(OR('1. Raw Data'!C5001<18, '1. Raw Data'!C5001>100), MEDIAN('1. Raw Data'!$C$2:$C$5001), '1. Raw Data'!C5001) -> 38 | D5001: Luxor | E5001: 45078 | F5001: 0 | G5001: 13412 | H5001: 44932 | I5001: Standard | J5001: 115 | K5001: Product_115 | L5001: =IF(OR('1. Raw Data'!L5001="Elec", '1. Raw Data'!L5001="elect"), "Electronics", '1. Raw Data'!L5001) -> Home Appliances | M5001: 1082.25 | N5001: =IF(ISBLANK('1. Raw Data'!N5001), MEDIAN('1. Raw Data'!$N$2:$N$5001), '1. Raw Data'!N5001) -> 684.52 | O5001: 2 | P5001: =IF(ISBLANK('1. Raw Data'!P5001), 0, '1. Raw Data'!P5001) -> 0 | Q5001: 505 | R5001: 3 | S5001: =M5001 * O5001 * (1 - P5001) -> 2164.5 | T5001: =S5001 - (N5001 * O5001) -> 795.46 | U5001: =T5001 / S5001 -> 0.36750289

Sheet 3. Pivot Analysis (Day 1 Focus)
A1: Pivot Table 1: Revenue & Profit by Category | I1: Pivot Table 2: Monthly Revenue & Order Trend | N1: Pivot Table 3: Top 15 Customers by Profitability | S1: Pivot Table 4: Regional Geographic Performance
A2: Row Labels | B2: Sum of Revenue | C2: Sum of Profit | D2: Average of Discount | E2: Count of OrderID | F2: Sum of Profit Margin | I2: Row Labels | J2: Sum of Revenue | K2: Count of OrderID | N2: Row Labels | O2: Sum of Profit | P2: Sum of Revenue | S2: Sum of Revenue | T2: Column Labels
A3: Clothing | B3: 2852855.4 | C3: 1200747.7 | D3: 0.033427192 | E3: 1243 | F3: 0.4208933 | I3: 2020 | J3: 2774136.8 | K3: 1203 | N3: Customer_135 | O3: 5316.58 | P3: 7464.15 | S3: Row Labels | T3: Express | U3: Same Day | V3: Standard | W3: Grand Total
A4: Electronics | B4: 2789081 | C4: 1208254.6 | D4: 0.03242915 | E4: 1235 | F4: 0.43320884 | I4: Jan | J4: 225464.4 | K4: 85 | N4: Customer_351 | O4: 5289.92 | P4: 7437.5 | S4: Alexandria | T4: 659577.64 | U4: 609719.39 | V4: 645738.52 | W4: 1915035.6
A5: Home Appliances | B5: 2876936.7 | C5: 1239616 | D5: 0.034136546 | E5: 1245 | F5: 0.43088054 | I5: Feb | J5: 205895.57 | K5: 86 | N5: Customer_4640 | O5: 5260.78 | P5: 7408.35 | S5: Aswan | T5: 640433.43 | U5: 662478.86 | V5: 673415.55 | W5: 1976327.8
A6: Sports | B6: 2879724 | C6: 1220508.6 | D6: 0.038410337 | E6: 1277 | F6: 0.42382833 | I6: Mar | J6: 221586.97 | K6: 96 | N6: Customer_4795 | O6: 5122.58 | P6: 7270.15 | S6: Cairo | T6: 591725.6 | U6: 610994.94 | V6: 690958.79 | W6: 1893679.3
I7: Apr | J7: 240352.23 | K7: 112 | N7: Customer_1497 | O7: 4976.62 | P7: 7124.2 | S7: Giza | T7: 623294.41 | U7: 537790.06 | V7: 579771.51 | W7: 1740856
I8: May | J8: 206010.66 | K8: 98 | N8: Customer_2943 | O8: 4819.32 | P8: 6966.9 | S8: Luxor | T8: 666703.67 | U8: 615456.47 | V8: 665353.03 | W8: 1947513.2
I9: Jun | J9: 241966.46 | K9: 100 | N9: Customer_1628 | O9: 4673.92 | P9: 6821.5 | S9: Mansoura | T9: 634331.62 | U9: 698256.99 | V9: 592596.6 | W9: 1925185.2
I10: Jul | J10: 279004.95 | K10: 115 | N10: Customer_2675 | O10: 4594.62 | P10: 6742.2 | S10: Grand Total | T10: 3816066.4 | U10: 3734696.7 | V10: 3847834 | W10: 11398597
I11: Aug | J11: 229336.9 | K11: 107 | N11: Customer_4827 | O11: 4543.68 | P11: 6691.25
I12: Sep | J12: 220634.3 | K12: 103 | N12: Customer_4548 | O12: 4514.23 | P12: 6661.8
I13: Oct | J13: 277187.5 | K13: 116 | N13: Customer_2856 | O13: 4390.8 | P13: 7383.5
I14: Nov | J14: 239278.31 | K14: 99 | N14: Customer_4228 | O14: 4389.1 | P14: 7323.35
I15: Dec | J15: 187418.58 | K15: 86 | N15: Customer_1606 | O15: 4353.75 | P15: 7332.25
I16: 2021 | J16: 2813407.5 | K16: 1189 | N16: Customer_2297 | O16: 4319.15 | P16: 7385.3
I17: Jan | J17: 205045.68 | K17: 87 | N17: Customer_2553 | O17: 4270.95 | P17: 7245.25
I18: Feb | J18: 208481.54 | K18: 82 | N18: Grand Total | O18: 70836 | P18: 107257.65
I19: Mar | J19: 234614.59 | K19: 107
I20: Apr | J20: 211446.99 | K20: 93
I21: May | J21: 324127.73 | K21: 127
I22: Jun | J22: 229382.06 | K22: 97
I23: Jul | J23: 260819.52 | K23: 107
I24: Aug | J24: 258694.3 | K24: 101
I25: Sep | J25: 238412.97 | K25: 94
I26: Oct | J26: 221364.2 | K26: 103
I27: Nov | J27: 202421.54 | K27: 99
I28: Dec | J28: 218596.43 | K28: 92
I29: 2022 | J29: 2617931.1 | K29: 1209
I30: Jan | J30: 252970.15 | K30: 101
... I67: Grand Total | J67: 11398597 | K67: 5000

Sheet 4. Summary (Day 2 Focus)
A1: TechNova Business KPIs (Day 2 Focus)
A3: Total Revenue | B3: =SUM('2. Cleaned Data'!S2:S5001) -> 11398597
A4: Total Profit | B4: =SUM('2. Cleaned Data'!T2:T5001) -> 4869126.9
A5: Gross Profit Margin (%) | B5: =B4 / B3 -> 0.42716896
A6: Total Orders (Records) | B6: =COUNTA('2. Cleaned Data'!G2:G5001)-1 -> 4999
A7: Unique Customers | B7: =COUNTA(_xlfn.UNIQUE('2. Cleaned Data'!A2:A5001)) -> 1433
A8: Average Order Value (AOV) | B8: =AVERAGE('2. Cleaned Data'!S2:S5001) -> 2279.7194
A9: Average Discount (%) | B9: =AVERAGE('2. Cleaned Data'!P2:P5001) -> 0.03463
A10: Churn Rate (%) | B10: =COUNTIF('2. Cleaned Data'!F:F, 1)/5000 -> 0.2892
A11: Active Customers | B11: =COUNTIF('2. Cleaned Data'!F:F, 0) -> 3554
A12: Churned Customers | B12: =COUNTIF('2. Cleaned Data'!F:F, 1) -> 1446
A15: Descriptive Statistics (Day 2 Focus)
A16: Mean Revenue | B16: =AVERAGE('2. Cleaned Data'!$S$2:$S$5001) -> 2279.7194
A17: Median Revenue | B17: =MEDIAN('2. Cleaned Data'!$S$2:$S$5001) -> 1832.4
A18: Standard Deviation | B18: =_xlfn.STDEV.S('2. Cleaned Data'!$S$2:$S$5001) -> 1730.1966
A19: Variance | B19: =_xlfn.VAR.S('2. Cleaned Data'!$S$2:$S$5001) -> 2993580.2
A20: Min Spend | B20: =MIN('2. Cleaned Data'!$S$2:$S$5001) -> 50.45
A21: Max Spend | B21: =MAX('2. Cleaned Data'!$S$2:$S$5001) -> 7481
A24: Outlier Detection (IQR) (Day 2 Focus)
A25: Q1 (25th Percentile) | B25: =_xlfn.QUARTILE.INC('2. Cleaned Data'!$S$2:$S$5001, 1) -> 886.3055
A26: Q3 (75th Percentile) | B26: =_xlfn.QUARTILE.INC('2. Cleaned Data'!$S$2:$S$5001, 3) -> 3381.378
A27: IQR (Inter Quartile Range) | B27: =B26 - B25 -> 2495.0725
A28: Upper Boundar | B28: =B26 + (1.5 * B27) -> 7123.9867
A29: Lower Boundary | B29: =B25 - (1.5 * B27) -> -2856.3032
